emp_ide/__init__.py
emp_ide/admin.py
emp_ide/apps.py
emp_ide/decorators.py
emp_ide/models.py
emp_ide/urls.py
emp_ide/views.py
emp_ide/migrations/0001_initial.py
emp_ide/migrations/__init__.py
emp_ide/static/css/app.a9b6e1cf.css
emp_ide/static/css/chunk-329d5946.5e39cfad.css
emp_ide/static/css/chunk-vendors.8a6af21e.css
emp_ide/static/fonts/MaterialIcons-Regular.012cf6a1.woff
emp_ide/static/fonts/MaterialIcons-Regular.570eb838.woff2
emp_ide/static/fonts/MaterialIcons-Regular.a37b0c01.ttf
emp_ide/static/fonts/MaterialIcons-Regular.e79bfd88.eot
emp_ide/static/img/iconfont.573255ce.svg
emp_ide/static/js/app.432c990d.js
emp_ide/static/js/app.432c990d.js.map
emp_ide/static/js/chunk-2d0c0e14.e4f25a38.js
emp_ide/static/js/chunk-2d0c0e14.e4f25a38.js.map
emp_ide/static/js/chunk-2d0d3720.f764eeca.js
emp_ide/static/js/chunk-2d0d3720.f764eeca.js.map
emp_ide/static/js/chunk-2d0e64c6.d56af125.js
emp_ide/static/js/chunk-2d0e64c6.d56af125.js.map
emp_ide/static/js/chunk-2d230ab1.d8b63db6.js
emp_ide/static/js/chunk-2d230ab1.d8b63db6.js.map
emp_ide/static/js/chunk-329d5946.f788fc45.js
emp_ide/static/js/chunk-329d5946.f788fc45.js.map
emp_ide/static/js/chunk-vendors.ec36a913.js
emp_ide/static/js/chunk-vendors.ec36a913.js.map
emp_ide/templates/.gitkeep
emp_ide/templates/index.html
1zlab_emp_ide-0.0.3.dist-info/AUTHORS
1zlab_emp_ide-0.0.3.dist-info/METADATA
1zlab_emp_ide-0.0.3.dist-info/WHEEL
1zlab_emp_ide-0.0.3.dist-info/pbr.json
1zlab_emp_ide-0.0.3.dist-info/top_level.txt
1zlab_emp_ide-0.0.3.dist-info/RECORD
